smoltorch/__init__.py
smoltorch/nn.py
smoltorch/optim.py
smoltorch/tensor.py
smoltorch-0.1.0.dist-info/METADATA
smoltorch-0.1.0.dist-info/WHEEL
smoltorch-0.1.0.dist-info/top_level.txt
smoltorch-0.1.0.dist-info/RECORD
