Metadata-Version: 2.4
Name: smoltorch
Version: 0.1.0
Summary: A tiny autograd engine and neural network library built from first principles
Author-email: Kashif <me@ifkash.dev>
License: MIT
Project-URL: Homepage, https://github.com/kashifulhaque/smoltorch
Project-URL: Repository, https://github.com/kashifulhaque/smoltorch
Project-URL: Issues, https://github.com/kashifulhaque/smoltorch/issues
Requires-Python: >=3.12
Requires-Dist: ipykernel>=7.1.0
Requires-Dist: ipython>=9.7.0
Requires-Dist: matplotlib>=3.10.7
Requires-Dist: mlx>=0.29.4
Requires-Dist: nbconvert>=7.16.6
Requires-Dist: numpy>=2.3.4
Requires-Dist: scikit-learn>=1.7.2
